sfdc_bulk/__init__.py
sfdc_bulk/api.py
sfdc_bulk-0.2.dist-info/DESCRIPTION.rst
sfdc_bulk-0.2.dist-info/METADATA
sfdc_bulk-0.2.dist-info/RECORD
sfdc_bulk-0.2.dist-info/WHEEL
sfdc_bulk-0.2.dist-info/metadata.json
sfdc_bulk-0.2.dist-info/top_level.txt
