Metadata-Version: 2.0
Name: sfdc-bulk
Version: 0.2
Summary: Python client library for SFDC bulk API
Home-page: https://github.com/donaldrauscher/sfdc-bulk
Author: Donald Rauscher
Author-email: donald.rauscher@gmail.com
License: MIT
Platform: UNKNOWN
Requires-Dist: pandas
Requires-Dist: pyyaml
Requires-Dist: requests
Requires-Dist: simple-salesforce
